sanic_mysql/__init__.py
sanic_mysql/core.py
sanic_mysql-0.0.5.dist-info/DESCRIPTION.rst
sanic_mysql-0.0.5.dist-info/METADATA
sanic_mysql-0.0.5.dist-info/RECORD
sanic_mysql-0.0.5.dist-info/WHEEL
sanic_mysql-0.0.5.dist-info/metadata.json
sanic_mysql-0.0.5.dist-info/top_level.txt
