Metadata-Version: 2.0
Name: sanic-mysql
Version: 0.0.5
Summary: Adds mysql support to sanic .
Home-page: https://github.com/jimgreat/sanic_mysql
Author: jimgreat
Author-email: UNKNOWN
License: MIT
Keywords: Sanic,mysql,aiomysql
Platform: UNKNOWN
Classifier: Programming Language :: Python :: 3.5
Classifier: Programming Language :: Python :: 3.6
Classifier: Programming Language :: Python :: 3 :: Only
Classifier: Topic :: Internet :: WWW/HTTP :: Session
Requires-Dist: Sanic
Requires-Dist: aiomysql
